my_package_devilshorn/__init__.py
my_package_devilshorn/add_num.py
my_package_devilshorn-0.2.dist-info/LICENSE
my_package_devilshorn-0.2.dist-info/METADATA
my_package_devilshorn-0.2.dist-info/WHEEL
my_package_devilshorn-0.2.dist-info/top_level.txt
my_package_devilshorn-0.2.dist-info/RECORD
