Metadata-Version: 2.1
Name: my-package-devilshorn
Version: 0.2
Summary: Just a test package
Home-page: https://github.com/Devilshorn999/my_package
Author: Indrajeet
Author-email: inder7171@gmail.com
Classifier: Programming Language :: Python :: 3
Classifier: License :: OSI Approved :: MIT License
Classifier: Operating System :: OS Independent
License-File: LICENSE
Requires-Dist: numpy (>=1.19.0)
